pliers/__init__.py
pliers/config.py
pliers/graph.py
pliers/version.py
pliers/converters/__init__.py
pliers/converters/audio.py
pliers/converters/base.py
pliers/converters/image.py
pliers/converters/iterators.py
pliers/converters/misc.py
pliers/converters/multistep.py
pliers/converters/video.py
pliers/converters/api/__init__.py
pliers/converters/api/google.py
pliers/converters/api/ibm.py
pliers/converters/api/microsoft.py
pliers/converters/api/revai.py
pliers/converters/api/wit.py
pliers/datasets/__init__.py
pliers/datasets/dictionaries.json
pliers/datasets/text.py
pliers/diagnostics/__init__.py
pliers/diagnostics/base.py
pliers/external/__init__.py
pliers/external/pysaliency/__init__.py
pliers/external/pysaliency/pySaliencyMap.py
pliers/external/pysaliency/pySaliencyMapDefs.py
pliers/external/tensorflow/__init__.py
pliers/external/tensorflow/classify_image.py
pliers/extractors/__init__.py
pliers/extractors/audio.py
pliers/extractors/base.py
pliers/extractors/image.py
pliers/extractors/misc.py
pliers/extractors/models.py
pliers/extractors/text.py
pliers/extractors/video.py
pliers/extractors/api/__init__.py
pliers/extractors/api/clarifai.py
pliers/extractors/api/google.py
pliers/extractors/api/microsoft.py
pliers/filters/__init__.py
pliers/filters/audio.py
pliers/filters/base.py
pliers/filters/image.py
pliers/filters/text.py
pliers/filters/video.py
pliers/stimuli/__init__.py
pliers/stimuli/api.py
pliers/stimuli/audio.py
pliers/stimuli/base.py
pliers/stimuli/compound.py
pliers/stimuli/image.py
pliers/stimuli/misc.py
pliers/stimuli/text.py
pliers/stimuli/video.py
pliers/support/__init__.py
pliers/support/decorators.py
pliers/support/download.py
pliers/support/due.py
pliers/support/exceptions.py
pliers/support/setup_yamnet.py
pliers/tests/__init__.py
pliers/tests/conftest.py
pliers/tests/test_config.py
pliers/tests/test_datasets.py
pliers/tests/test_diagnostics.py
pliers/tests/test_graph.py
pliers/tests/test_io.py
pliers/tests/test_scikit.py
pliers/tests/test_stims.py
pliers-0.4.2.dist-info/LICENSE
pliers-0.4.2.dist-info/METADATA
pliers-0.4.2.dist-info/WHEEL
pliers-0.4.2.dist-info/top_level.txt
pliers-0.4.2.dist-info/RECORD
