Metadata-Version: 2.1
Name: pliers
Version: 0.4.2
Summary: Multimodal feature extraction in Python
Home-page: http://github.com/psychoinformaticslab/pliers
Maintainer: Tal Yarkoni
Maintainer-email: tyarkoni@gmail.com
License: MIT
Download-URL: https://github.com/psychoinformaticslab/pliers/archive/0.4.2.tar.gz
Platform: UNKNOWN
Requires-Python: >=3.6
Requires-Dist: python-magic
Requires-Dist: numpy (>=1.13)
Requires-Dist: nltk (>=3.0)
Requires-Dist: moviepy (>=0.2)
Requires-Dist: pandas (>=0.24)
Requires-Dist: pillow
Requires-Dist: requests
Requires-Dist: scipy (>=0.13)
Requires-Dist: imageio (>=2.3)
Requires-Dist: tqdm
Requires-Dist: psutil
Provides-Extra: all
Requires-Dist: clarifai-grpc ; extra == 'all'
Requires-Dist: duecredit ; extra == 'all'
Requires-Dist: face-recognition ; extra == 'all'
Requires-Dist: keras ; extra == 'all'
Requires-Dist: python-twitter ; extra == 'all'
Requires-Dist: gensim ; extra == 'all'
Requires-Dist: google-api-python-client ; extra == 'all'
Requires-Dist: google-compute-engine ; extra == 'all'
Requires-Dist: librosa (>=0.6.3) ; extra == 'all'
Requires-Dist: numba (<=0.48) ; extra == 'all'
Requires-Dist: matplotlib ; extra == 'all'
Requires-Dist: opencv-python ; extra == 'all'
Requires-Dist: openpyxl ; extra == 'all'
Requires-Dist: pathos ; extra == 'all'
Requires-Dist: pygraphviz ; extra == 'all'
Requires-Dist: pysrt ; extra == 'all'
Requires-Dist: pytesseract ; extra == 'all'
Requires-Dist: scikit-learn ; extra == 'all'
Requires-Dist: seaborn ; extra == 'all'
Requires-Dist: spacy (>=3.2.0) ; extra == 'all'
Requires-Dist: SpeechRecognition (>=3.6.0) ; extra == 'all'
Requires-Dist: tensorflow (>=2.4.0) ; extra == 'all'
Requires-Dist: torch ; extra == 'all'
Requires-Dist: transformers ; extra == 'all'
Requires-Dist: xlrd ; extra == 'all'
Requires-Dist: rev-ai ; extra == 'all'
Requires-Dist: tensorflow-hub ; extra == 'all'
Requires-Dist: tensorflow-text ; extra == 'all'
Provides-Extra: docs
Requires-Dist: sphinx (>=4) ; extra == 'docs'
Requires-Dist: pytest ; extra == 'docs'
Requires-Dist: sphinx-autodoc-typehints ; extra == 'docs'
Requires-Dist: sphinx-argparse ; extra == 'docs'
Requires-Dist: ipywidgets ; extra == 'docs'
Requires-Dist: nbsphinx ; extra == 'docs'
Requires-Dist: sphinx-rtd-theme ; extra == 'docs'
Requires-Dist: matplotlib ; extra == 'docs'
Provides-Extra: tests
Requires-Dist: pytest ; extra == 'tests'
Requires-Dist: coveralls ; extra == 'tests'
Requires-Dist: pytest-cov ; extra == 'tests'
Requires-Dist: pytest-forked ; extra == 'tests'
Requires-Dist: pytest-xdist ; extra == 'tests'
